typodoo.py
typodoo_activate.pth
typodoo-0.4.1.dist-info/METADATA
typodoo-0.4.1.dist-info/WHEEL
typodoo-0.4.1.dist-info/licenses/LICENSE.txt
typodoo-0.4.1.dist-info/RECORD
