Metadata-Version: 2.3
Name: typodoo
Version: 0.4.1
Summary: Towards idiomatic Python with types for the Odoo ORM
Project-URL: Documentation, https://github.com/sbidoul/typodoo#readme
Project-URL: Issues, https://github.com/sbidoul/typodoo/issues
Project-URL: Source, https://github.com/sbidoul/typodoo
Author-email: Stéphane Bidoul <stephane.bidoul@acsone.eu>
License: MIT
Classifier: Development Status :: 2 - Pre-Alpha
Classifier: Framework :: Odoo
Classifier: Programming Language :: Python
Classifier: Programming Language :: Python :: 3.10
Requires-Python: >=3.10
Requires-Dist: wrapt
